Metadata-Version: 2.1
Name: odoo-addon-account-cutoff-accrual-picking
Version: 15.0.1.0.0.10
Summary: Accrued expense & accrued revenue from pickings
Home-page: https://github.com/OCA/account-closing
Author: Akretion,Odoo Community Association (OCA)
Author-email: support@odoo-community.org
License: AGPL-3
Platform: UNKNOWN
Classifier: Programming Language :: Python
Classifier: Framework :: Odoo
Classifier: Framework :: Odoo :: 15.0
Classifier: License :: OSI Approved :: GNU Affero General Public License v3
Requires-Python: >=3.8
Requires-Dist: odoo-addon-account-cutoff-base <15.1dev,>=15.0dev
Requires-Dist: odoo <15.1dev,>=15.0a
